Metadata-Version: 1.0
Name: oauth
Version: 1.0
Summary: Library for OAuth
Home-page: http://code.google.com/p/oauth
Author: Leah Culver
Author-email: leah.culver@gmail.com
License: UNKNOWN
Platform: UNKNOWN
